.gitignore
.travis.yml
LICENSE
README.rst
setup.cfg
setup.py
tox.ini
d3t/__init__.py
d3t/proxies.py
d3t/rendering.py
d3t/selections.py
d3t/signals.py
d3t/watcher.py
django_3t.egg-info/PKG-INFO
django_3t.egg-info/SOURCES.txt
django_3t.egg-info/dependency_links.txt
django_3t.egg-info/not-zip-safe
django_3t.egg-info/requires.txt
django_3t.egg-info/top_level.txt
tests/__init__.py
tests/acceptance/__init__.py
tests/acceptance/test_block_api.py
tests/acceptance/test_node_api.py
tests/acceptance/test_template_api.py
tests/project/__init__.py
tests/project/settings.py
tests/project/urls.py
tests/project/templates/fragment.html
tests/project/templates/root.html
tests/project/templatetags/__init__.py
tests/project/templatetags/tags.py
tests/unit/__init__.py
tests/unit/test_proxies.py
tests/unit/test_rendering.py
tests/unit/test_selections.py
tests/unit/test_watcher.py