Metadata-Version: 2.1
Name: django-3t
Version: 1.0.0a1
Summary: Django 3T is a Django Template Testing Tool which aims to help developers to write better tests where the Django template engine is involved.
Home-page: https://github.com/yurifari/django-3t
Author: Yuri Farina
Author-email: me@yurifarina.com
License: MIT
Project-URL: Source, https://github.com/yurifari/django-3t
Project-URL: Tracker, https://github.com/yurifari/django-3t/issues
Keywords: django,template,test,unittest
Platform: any
Classifier: Development Status :: 3 - Alpha
Classifier: Intended Audience :: Developers
Classifier: License :: OSI Approved :: MIT License
Classifier: Operating System :: OS Independent
Classifier: Programming Language :: Python
Classifier: Programming Language :: Python :: 3
Classifier: Programming Language :: Python :: 3 :: Only
Classifier: Programming Language :: Python :: 3.6
Classifier: Programming Language :: Python :: 3.7
Classifier: Programming Language :: Python :: 3.8
